Utils/CSV_to_JSON.py
Utils/CreateGitBranch.py
Utils/PythonPackageCleanUP.py
Utils/PythonPackageUpload.py
Utils/__init__.py
NashUtils-1.1.1.dist-info/METADATA
NashUtils-1.1.1.dist-info/WHEEL
NashUtils-1.1.1.dist-info/top_level.txt
NashUtils-1.1.1.dist-info/RECORD
