Metadata-Version: 2.1
Name: NashUtils
Version: 1.1.1
Summary: This package contains Utlitiy tools for Python
Home-page: https://github.com/Althafnash/NashUtils.git
Author: Mohammed Althaf
Author-email: althafnash14@gmail.com
Classifier: Programming Language :: Python :: 3
Classifier: License :: OSI Approved :: MIT License
Classifier: Operating System :: OS Independent
Requires-Python: >=3.6
